<hierarchy rotation="0">
    <node bounds="[0,0][1080,1776]" checkable="false" checked="false" class="android.widget.FrameLayout" clickable="false" content-desc="" enabled="true" focusable="false" focused="false" index="0" long-clickable="false" package="com.instagram.android" password="false" resource-id="" scrollable="false" selected="false" text="">
        <node bounds="[0,0][1080,1776]" checkable="false" checked="false" class="android.widget.LinearLayout" clickable="false" content-desc="" enabled="true" focusable="false" focused="false" index="0" long-clickable="false" package="com.instagram.android" password="false" resource-id="" scrollable="false" selected="false" text="">
            <node bounds="[0,0][1080,1776]" checkable="false" checked="false" class="android.widget.FrameLayout" clickable="false" content-desc="" enabled="true" focusable="false" focused="false" index="0" long-clickable="false" package="com.instagram.android" password="false" resource-id="" scrollable="false" selected="false" text="">
                <node bounds="[0,0][1080,1776]" checkable="false" checked="false" class="android.widget.LinearLayout" clickable="false" content-desc="" enabled="true" focusable="false" focused="false" index="0" long-clickable="false" package="com.instagram.android" password="false" resource-id="com.instagram.android:id/action_bar_root" scrollable="false" selected="false" text="">
                    <node bounds="[0,0][1080,1776]" checkable="false" checked="false" class="android.widget.FrameLayout" clickable="false" content-desc="" enabled="true" focusable="false" focused="false" index="0" long-clickable="false" package="com.instagram.android" password="false" resource-id="android:id/content" scrollable="false" selected="false" text="">
                        <node bounds="[0,0][1080,1776]" checkable="false" checked="false" class="android.widget.FrameLayout" clickable="false" content-desc="" enabled="true" focusable="false" focused="false" index="0" long-clickable="false" package="com.instagram.android" password="false" resource-id="com.instagram.android:id/swipe_navigation_container" scrollable="false" selected="false" text="">
                            <node bounds="[0,0][1080,1776]" checkable="false" checked="false" class="android.widget.FrameLayout" clickable="false" content-desc="" enabled="true" focusable="false" focused="false" index="0" long-clickable="false" package="com.instagram.android" password="false" resource-id="" scrollable="false" selected="false" text="">
                                <node bounds="[0,72][1080,1776]" checkable="false" checked="false" class="android.widget.FrameLayout" clickable="false" content-desc="" enabled="true" focusable="false" focused="false" index="1" long-clickable="false" package="com.instagram.android" password="false" resource-id="com.instagram.android:id/layout_container_main_panel" scrollable="false" selected="false" text="">
                                    <node bounds="[0,72][1080,1632]" checkable="false" checked="false" class="android.widget.FrameLayout" clickable="false" content-desc="" enabled="true" focusable="false" focused="false" index="0" long-clickable="false" package="com.instagram.android" password="false" resource-id="com.instagram.android:id/layout_container_main" scrollable="false" selected="false" text="">
                                        <node bounds="[0,72][1080,1632]" checkable="false" checked="false" class="android.widget.FrameLayout" clickable="false" content-desc="" enabled="true" focusable="false" focused="false" index="0" long-clickable="false" package="com.instagram.android" password="false" resource-id="com.instagram.android:id/layout_listview_parent_container" scrollable="false" selected="false" text="">
                                            <node bounds="[0,72][1080,1632]" checkable="false" checked="false" class="android.widget.FrameLayout" clickable="false" content-desc="" enabled="true" focusable="false" focused="false" index="0" long-clickable="false" package="com.instagram.android" password="false" resource-id="com.instagram.android:id/sticky_header_list" scrollable="false" selected="false" text="">
                                                <node bounds="[0,72][1080,1632]" checkable="false" checked="false" class="android.widget.ListView" clickable="true" content-desc="" enabled="true" focusable="true" focused="true" index="0" long-clickable="false" package="com.instagram.android" password="false" resource-id="android:id/list" scrollable="true" selected="false" text="">
                                                    <node bounds="[0,72][1080,228]" checkable="false" checked="false" class="android.widget.FrameLayout" clickable="false" content-desc="" enabled="true" focusable="false" focused="false" index="0" long-clickable="false" package="com.instagram.android" password="false" resource-id="com.instagram.android:id/zoomable_view_container" scrollable="false" selected="false" text="">
                                                        <node bounds="[0,72][1080,228]" checkable="false" checked="false" class="android.widget.FrameLayout" clickable="true" content-desc="" enabled="true" focusable="true" focused="false" index="0" long-clickable="false" package="com.instagram.android" password="false" resource-id="com.instagram.android:id/media_group" scrollable="false" selected="false" text="">
                                                            <node bounds="[0,72][1080,228]" checkable="false" checked="false" class="android.view.ViewGroup" clickable="false" content-desc="" enabled="true" focusable="false" focused="false" index="0" long-clickable="false" package="com.instagram.android" password="false" resource-id="com.instagram.android:id/row_feed_photo_product_tag_hints" scrollable="false" selected="false" text="" />
                                                            <node bounds="[0,72][1080,228]" checkable="false" checked="false" class="android.widget.FrameLayout" clickable="false" content-desc="Image" enabled="true" focusable="false" focused="false" index="1" long-clickable="false" package="com.instagram.android" password="false" resource-id="com.instagram.android:id/row_feed_photo_imageview" scrollable="false" selected="false" text="">
                                                                <node bounds="[0,72][1080,228]" checkable="false" checked="false" class="android.widget.ImageView" clickable="false" content-desc="" enabled="true" focusable="false" focused="false" index="0" long-clickable="false" package="com.instagram.android" password="false" resource-id="" scrollable="false" selected="false" text="" />
                                                            </node>
                                                            <node bounds="[0,72][1080,228]" checkable="false" checked="false" class="android.view.ViewGroup" clickable="false" content-desc="" enabled="true" focusable="false" focused="false" index="2" long-clickable="false" package="com.instagram.android" password="false" resource-id="com.instagram.android:id/row_feed_photo_media_tag_hints" scrollable="false" selected="false" text="" />
                                                            <node bounds="[0,72][1080,228]" checkable="false" checked="false" class="android.widget.FrameLayout" clickable="false" content-desc="" enabled="true" focusable="false" focused="false" index="3" long-clickable="false" package="com.instagram.android" password="false" resource-id="com.instagram.android:id/row_feed_media_actions" scrollable="false" selected="false" text="" />
                                                        </node>
                                                    </node>
                                                    <node bounds="[0,228][1080,366]" checkable="false" checked="false" class="android.widget.RelativeLayout" clickable="false" content-desc="" enabled="true" focusable="false" focused="false" index="1" long-clickable="false" package="com.instagram.android" password="false" resource-id="com.instagram.android:id/row_feed_view_group_buttons" scrollable="false" selected="false" text="">
                                                        <node bounds="[18,228][138,366]" checkable="false" checked="false" class="android.widget.ImageView" clickable="true" content-desc="Like" enabled="true" focusable="false" focused="false" index="0" long-clickable="false" package="com.instagram.android" password="false" resource-id="com.instagram.android:id/row_feed_button_like" scrollable="false" selected="false" text="" />
                                                        <node bounds="[138,228][258,366]" checkable="false" checked="false" class="android.widget.ImageView" clickable="true" content-desc="Comment" enabled="true" focusable="false" focused="false" index="1" long-clickable="false" package="com.instagram.android" password="false" resource-id="com.instagram.android:id/row_feed_button_comment" scrollable="false" selected="false" text="" />
                                                        <node bounds="[258,228][378,366]" checkable="false" checked="false" class="android.widget.ImageView" clickable="true" content-desc="Share" enabled="true" focusable="false" focused="false" index="2" long-clickable="false" package="com.instagram.android" password="false" resource-id="com.instagram.android:id/row_feed_button_share" scrollable="false" selected="false" text="" />
                                                        <node bounds="[942,228][1062,360]" checkable="false" checked="false" class="android.widget.ImageView" clickable="true" content-desc="Save" enabled="true" focusable="false" focused="false" index="3" long-clickable="true" package="com.instagram.android" password="false" resource-id="com.instagram.android:id/row_feed_button_save" scrollable="false" selected="false" text="" />
                                                    </node>
                                                    <node bounds="[0,366][1080,427]" checkable="false" checked="false" class="android.widget.LinearLayout" clickable="false" content-desc="" enabled="true" focusable="false" focused="false" index="2" long-clickable="false" package="com.instagram.android" password="false" resource-id="com.instagram.android:id/row_feed_media_feedback_content" scrollable="false" selected="false" text="">
                                                        <node bounds="[0,366][1080,415]" checkable="false" checked="false" class="android.widget.RelativeLayout" clickable="false" content-desc="" enabled="true" focusable="false" focused="false" index="0" long-clickable="false" package="com.instagram.android" password="false" resource-id="com.instagram.android:id/like_row" scrollable="false" selected="false" text="">
                                                            <node bounds="[42,366][1038,415]" checkable="false" checked="false" class="android.widget.TextView" clickable="true" content-desc="" enabled="true" focusable="true" focused="false" index="0" long-clickable="true" package="com.instagram.android" password="false" resource-id="com.instagram.android:id/row_feed_textview_likes" scrollable="false" selected="false" text="737,739 likes" />
                                                        </node>
                                                    </node>
                                                    <node bounds="[0,427][1080,549]" checkable="false" checked="false" class="android.widget.LinearLayout" clickable="false" content-desc="" enabled="true" focusable="false" focused="false" index="3" long-clickable="false" package="com.instagram.android" password="false" resource-id="" scrollable="false" selected="false" text="">
                                                        <node bounds="[42,427][1080,537]" checkable="false" checked="false" class="com.instagram.ui.widget.textview.IgTextLayoutView" clickable="false" content-desc="" enabled="true" focusable="true" focused="false" index="0" long-clickable="false" package="com.instagram.android" password="false" resource-id="com.instagram.android:id/row_feed_comment_textview_layout" scrollable="false" selected="false" text="instagram Artist Evgeny Ches (@ches_ches) paints realistic animals and street graffiti on cello&#8230; more">
                                                            <node bounds="[42,427][231,482]" checkable="false" checked="false" class="" clickable="true" content-desc="instagram" enabled="true" focusable="true" focused="false" index="0" long-clickable="false" package="" password="false" resource-id="" scrollable="false" selected="false" text="" />
                                                            <node bounds="[241,427][989,482]" checkable="false" checked="false" class="" clickable="true" content-desc="Artist Evgeny Ches (@ches_ches) paints realistic animals and street graffiti on cello" enabled="true" focusable="true" focused="false" index="1" long-clickable="false" package="" password="false" resource-id="" scrollable="false" selected="false" text="" />
                                                            <node bounds="[241,427][989,482]" checkable="false" checked="false" class="" clickable="true" content-desc="Artist Evgeny Ches (@ches_ches) paints realistic animals and street graffiti on cello" enabled="true" focusable="true" focused="false" index="2" long-clickable="false" package="" password="false" resource-id="" scrollable="false" selected="false" text="" />
                                                            <node bounds="[241,427][989,482]" checkable="false" checked="false" class="" clickable="true" content-desc="Artist Evgeny Ches (@ches_ches) paints realistic animals and street graffiti on cello" enabled="true" focusable="true" focused="false" index="3" long-clickable="false" package="" password="false" resource-id="" scrollable="false" selected="false" text="" />
                                                        </node>
                                                    </node>
                                                    <node bounds="[0,549][1080,610]" checkable="false" checked="false" class="android.widget.TextView" clickable="true" content-desc="" enabled="true" focusable="false" focused="false" index="4" long-clickable="false" package="com.instagram.android" password="false" resource-id="com.instagram.android:id/row_feed_view_all_comments_text" scrollable="false" selected="false" text="View all 6,830 comments" />
                                                    <node bounds="[0,610][1080,842]" checkable="false" checked="false" class="android.widget.LinearLayout" clickable="false" content-desc="" enabled="true" focusable="false" focused="false" index="5" long-clickable="false" package="com.instagram.android" password="false" resource-id="" scrollable="false" selected="false" text="">
                                                        <node bounds="[42,610][954,830]" checkable="false" checked="false" class="com.instagram.ui.widget.textview.IgTextLayoutView" clickable="false" content-desc="" enabled="true" focusable="true" focused="false" index="0" long-clickable="false" package="com.instagram.android" password="false" resource-id="com.instagram.android:id/row_feed_comment_textview_layout" scrollable="false" selected="false" text="kkout @instagram @ches_ches Does he collect and recycle these or he leaves them at the forests? Given that the planet is dying I'd hate to see more pollution.">
                                                            <node bounds="[42,610][145,665]" checkable="false" checked="false" class="" clickable="true" content-desc="kkout" enabled="true" focusable="true" focused="false" index="0" long-clickable="false" package="" password="false" resource-id="" scrollable="false" selected="false" text="" />
                                                            <node bounds="[42,610][922,665]" checkable="false" checked="false" class="" clickable="true" content-desc="kkout @instagram @ches_ches Does he collect and recycle these or he leaves them at the forests? Given that the planet is dying I'd hate to see more pollution." enabled="true" focusable="true" focused="false" index="1" long-clickable="false" package="" password="false" resource-id="" scrollable="false" selected="false" text="" />
                                                            <node bounds="[42,610][922,665]" checkable="false" checked="false" class="" clickable="true" content-desc="kkout @instagram @ches_ches Does he collect and recycle these or he leaves them at the forests? Given that the planet is dying I'd hate to see more pollution." enabled="true" focusable="true" focused="false" index="2" long-clickable="false" package="" password="false" resource-id="" scrollable="false" selected="false" text="" />
                                                        </node>
                                                        <node bounds="[954,610][1080,646]" checkable="false" checked="false" class="android.widget.FrameLayout" clickable="true" content-desc="Tap to like comment" enabled="true" focusable="false" focused="false" index="1" long-clickable="false" package="com.instagram.android" password="false" resource-id="" scrollable="false" selected="false" text="">
                                                            <node bounds="[996,610][1032,646]" checkable="false" checked="false" class="android.widget.ImageView" clickable="false" content-desc="" enabled="true" focusable="false" focused="false" index="0" long-clickable="false" package="com.instagram.android" password="false" resource-id="com.instagram.android:id/row_feed_comment_like_button" scrollable="false" selected="false" text="" />
                                                        </node>
                                                    </node>
                                                    <node bounds="[0,842][1080,964]" checkable="false" checked="false" class="android.widget.LinearLayout" clickable="false" content-desc="" enabled="true" focusable="false" focused="false" index="6" long-clickable="false" package="com.instagram.android" password="false" resource-id="" scrollable="false" selected="false" text="">
                                                        <node bounds="[69,842][75,952]" checkable="false" checked="false" class="android.view.View" clickable="false" content-desc="" enabled="true" focusable="false" focused="false" index="0" long-clickable="false" package="com.instagram.android" password="false" resource-id="com.instagram.android:id/row_feed_comment_textview_child_comment_indent" scrollable="false" selected="false" text="" />
                                                        <node bounds="[102,842][954,952]" checkable="false" checked="false" class="com.instagram.ui.widget.textview.IgTextLayoutView" clickable="false" content-desc="" enabled="true" focusable="true" focused="false" index="1" long-clickable="false" package="com.instagram.android" password="false" resource-id="com.instagram.android:id/row_feed_comment_textview_layout" scrollable="false" selected="false" text="ches_ches @kkout all Cellograffiti are removed &#128076;&#127997;">
                                                            <node bounds="[102,842][299,897]" checkable="false" checked="false" class="" clickable="true" content-desc="ches_ches" enabled="true" focusable="true" focused="false" index="0" long-clickable="false" package="" password="false" resource-id="" scrollable="false" selected="false" text="" />
                                                            <node bounds="[102,842][797,897]" checkable="false" checked="false" class="" clickable="true" content-desc="ches_ches @kkout all Cellograffiti are removed &#128076;&#127997;" enabled="true" focusable="true" focused="false" index="1" long-clickable="false" package="" password="false" resource-id="" scrollable="false" selected="false" text="" />
                                                        </node>
                                                        <node bounds="[954,842][1080,878]" checkable="false" checked="false" class="android.widget.FrameLayout" clickable="true" content-desc="Tap to like comment" enabled="true" focusable="false" focused="false" index="2" long-clickable="false" package="com.instagram.android" password="false" resource-id="" scrollable="false" selected="false" text="">
                                                            <node bounds="[996,842][1032,878]" checkable="false" checked="false" class="android.widget.ImageView" clickable="false" content-desc="" enabled="true" focusable="false" focused="false" index="0" long-clickable="false" package="com.instagram.android" password="false" resource-id="com.instagram.android:id/row_feed_comment_like_button" scrollable="false" selected="false" text="" />
                                                        </node>
                                                    </node>
                                                    <node bounds="[0,964][1080,1005]" checkable="false" checked="false" class="android.widget.FrameLayout" clickable="false" content-desc="" enabled="true" focusable="false" focused="false" index="8" long-clickable="false" package="com.instagram.android" password="false" resource-id="" scrollable="false" selected="false" text="">
                                                        <node bounds="[0,964][1080,1005]" checkable="false" checked="false" class="android.widget.TextView" clickable="true" content-desc="" enabled="true" focusable="true" focused="false" index="0" long-clickable="true" package="com.instagram.android" password="false" resource-id="" scrollable="false" selected="false" text="2 days ago" />
                                                    </node>
                                                    <node bounds="[0,1005][1080,1041]" checkable="false" checked="false" class="android.view.View" clickable="false" content-desc="" enabled="true" focusable="false" focused="false" index="9" long-clickable="false" package="com.instagram.android" password="false" resource-id="" scrollable="false" selected="false" text="" />
                                                    <node bounds="[0,1041][1080,1197]" checkable="false" checked="false" class="android.widget.LinearLayout" clickable="false" content-desc="" enabled="true" focusable="false" focused="false" index="10" long-clickable="false" package="com.instagram.android" password="false" resource-id="" scrollable="false" selected="false" text="">
                                                        <node bounds="[0,1041][1080,1197]" checkable="false" checked="false" class="android.widget.FrameLayout" clickable="false" content-desc="" enabled="true" focusable="false" focused="false" index="0" long-clickable="false" package="com.instagram.android" password="false" resource-id="com.instagram.android:id/row_feed_profile_header_container" scrollable="false" selected="false" text="">
                                                            <node bounds="[0,1041][1080,1197]" checkable="false" checked="false" class="android.widget.RelativeLayout" clickable="true" content-desc="" enabled="true" focusable="false" focused="false" index="0" long-clickable="false" package="com.instagram.android" password="false" resource-id="com.instagram.android:id/row_feed_profile_header" scrollable="false" selected="false" text="">
                                                                <node bounds="[33,1065][141,1173]" checkable="false" checked="false" class="android.widget.FrameLayout" clickable="true" content-desc="" enabled="true" focusable="false" focused="false" index="0" long-clickable="false" package="com.instagram.android" password="false" resource-id="com.instagram.android:id/avatar_container" scrollable="false" selected="false" text="">
                                                                    <node bounds="[42,1074][132,1164]" checkable="false" checked="false" class="android.widget.ImageView" clickable="false" content-desc="Profile picture" enabled="true" focusable="false" focused="false" index="0" long-clickable="false" package="com.instagram.android" password="false" resource-id="com.instagram.android:id/row_feed_photo_profile_imageview" scrollable="false" selected="false" text="" />
                                                                </node>
                                                                <node bounds="[141,1041][1080,1197]" checkable="false" checked="false" class="android.widget.LinearLayout" clickable="false" content-desc="" enabled="true" focusable="false" focused="false" index="1" long-clickable="false" package="com.instagram.android" password="false" resource-id="" scrollable="false" selected="false" text="">
                                                                    <node bounds="[141,1041][921,1197]" checkable="false" checked="false" class="android.widget.LinearLayout" clickable="false" content-desc="" enabled="true" focusable="false" focused="false" index="0" long-clickable="false" package="com.instagram.android" password="false" resource-id="com.instagram.android:id/row_feed_photo_media_metadata" scrollable="false" selected="false" text="">
                                                                        <node bounds="[141,1094][365,1143]" checkable="false" checked="false" class="android.widget.LinearLayout" clickable="false" content-desc="" enabled="true" focusable="false" focused="false" index="0" long-clickable="false" package="com.instagram.android" password="false" resource-id="" scrollable="false" selected="false" text="">
                                                                            <node bounds="[141,1094][365,1143]" checkable="false" checked="false" class="android.widget.TextView" clickable="true" content-desc="" enabled="true" focusable="false" focused="false" index="0" long-clickable="false" package="com.instagram.android" password="false" resource-id="com.instagram.android:id/row_feed_photo_profile_name" scrollable="false" selected="false" text="mileycyrus" />
                                                                        </node>
                                                                    </node>
                                                                    <node bounds="[954,1041][1080,1197]" checkable="false" checked="false" class="android.widget.LinearLayout" clickable="false" content-desc="" enabled="true" focusable="false" focused="false" index="1" long-clickable="false" package="com.instagram.android" password="false" resource-id="" scrollable="false" selected="false" text="">
                                                                        <node bounds="[954,1041][1080,1197]" checkable="false" checked="false" class="android.widget.ImageView" clickable="true" content-desc="Options" enabled="true" focusable="false" focused="false" index="0" long-clickable="false" package="com.instagram.android" password="false" resource-id="com.instagram.android:id/media_option_button" scrollable="false" selected="false" text="" />
                                                                    </node>
                                                                </node>
                                                            </node>
                                                            <node bounds="[0,1196][1080,1197]" checkable="false" checked="false" class="android.view.View" clickable="false" content-desc="" enabled="true" focusable="false" focused="false" index="1" long-clickable="false" package="com.instagram.android" password="false" resource-id="com.instagram.android:id/divider" scrollable="false" selected="false" text="" />
                                                        </node>
                                                    </node>
                                                    <node bounds="[0,1197][1080,1632]" checkable="false" checked="false" class="android.widget.FrameLayout" clickable="true" content-desc="" enabled="true" focusable="true" focused="false" index="11" long-clickable="false" package="com.instagram.android" password="false" resource-id="com.instagram.android:id/carousel_media_group" scrollable="false" selected="false" text="">
                                                        <node bounds="[0,1197][1080,1632]" checkable="false" checked="false" class="android.widget.FrameLayout" clickable="false" content-desc="" enabled="true" focusable="false" focused="false" index="0" long-clickable="false" package="com.instagram.android" password="false" resource-id="com.instagram.android:id/row_carousel_media_actions" scrollable="false" selected="false" text="" />
                                                        <node bounds="[0,1197][1080,1632]" checkable="false" checked="false" class="android.widget.FrameLayout" clickable="false" content-desc="" enabled="true" focusable="false" focused="false" index="1" long-clickable="false" package="com.instagram.android" password="false" resource-id="com.instagram.android:id/carousel_viewpager" scrollable="false" selected="false" text="">
                                                            <node bounds="[0,1197][1080,1632]" checkable="false" checked="false" class="android.widget.FrameLayout" clickable="true" content-desc="" enabled="true" focusable="true" focused="false" index="0" long-clickable="false" package="com.instagram.android" password="false" resource-id="" scrollable="false" selected="false" text="">
                                                                <node bounds="[0,1197][1080,1632]" checkable="false" checked="false" class="android.widget.FrameLayout" clickable="false" content-desc="Photo 2 of 2 by Miley Cyrus" enabled="true" focusable="false" focused="false" index="0" long-clickable="false" package="com.instagram.android" password="false" resource-id="com.instagram.android:id/carousel_image" scrollable="false" selected="false" text="">
                                                                    <node bounds="[0,1197][1080,1632]" checkable="false" checked="false" class="android.widget.ImageView" clickable="false" content-desc="" enabled="true" focusable="false" focused="false" index="0" long-clickable="false" package="com.instagram.android" password="false" resource-id="" scrollable="false" selected="false" text="" />
                                                                </node>
                                                                <node bounds="[0,1197][1080,1632]" checkable="false" checked="false" class="android.view.ViewGroup" clickable="false" content-desc="" enabled="true" focusable="false" focused="false" index="1" long-clickable="false" package="com.instagram.android" password="false" resource-id="com.instagram.android:id/row_feed_photo_product_tag_hints" scrollable="false" selected="false" text="" />
                                                                <node bounds="[0,1197][1080,1632]" checkable="false" checked="false" class="android.view.ViewGroup" clickable="false" content-desc="" enabled="true" focusable="false" focused="false" index="2" long-clickable="false" package="com.instagram.android" password="false" resource-id="com.instagram.android:id/row_feed_photo_media_tag_hints" scrollable="false" selected="false" text="" />
                                                            </node>
                                                        </node>
                                                        <node bounds="[913,1197][1080,1320]" checkable="false" checked="false" class="android.widget.FrameLayout" clickable="false" content-desc="" enabled="true" focusable="false" focused="false" index="2" long-clickable="false" package="com.instagram.android" password="false" resource-id="com.instagram.android:id/carousel_bumping_text_indicator_row" scrollable="false" selected="false" text="">
                                                            <node bounds="[913,1239][1038,1320]" checkable="false" checked="false" class="android.widget.TextView" clickable="false" content-desc="" enabled="true" focusable="false" focused="false" index="0" long-clickable="false" package="com.instagram.android" password="false" resource-id="com.instagram.android:id/carousel_bumping_text_indicator" scrollable="false" selected="false" text="2/2" />
                                                        </node>
                                                    </node>
                                                </node>
                                            </node>
                                        </node>
                                    </node>
                                    <node bounds="[0,72][1080,237]" checkable="false" checked="false" class="android.widget.FrameLayout" clickable="false" content-desc="" enabled="true" focusable="false" focused="false" index="1" long-clickable="false" package="com.instagram.android" password="false" resource-id="com.instagram.android:id/action_bar_container" scrollable="false" selected="false" text="">
                                        <node bounds="[0,72][1080,216]" checkable="false" checked="false" class="android.widget.FrameLayout" clickable="false" content-desc="" enabled="true" focusable="false" focused="false" index="0" long-clickable="false" package="com.instagram.android" password="false" resource-id="com.instagram.android:id/action_bar_wrapper" scrollable="false" selected="false" text="">
                                            <node bounds="[0,72][1080,216]" checkable="false" checked="false" class="android.widget.LinearLayout" clickable="true" content-desc="" enabled="true" focusable="false" focused="false" index="0" long-clickable="false" package="com.instagram.android" password="false" resource-id="com.instagram.android:id/action_bar" scrollable="false" selected="false" text="">
                                                <node bounds="[0,72][144,216]" checkable="false" checked="false" class="android.widget.ImageView" clickable="true" content-desc="Camera" enabled="true" focusable="false" focused="false" index="0" long-clickable="false" package="com.instagram.android" password="false" resource-id="com.instagram.android:id/action_bar_left_button" scrollable="false" selected="false" text="" />
                                                <node bounds="[144,72][792,216]" checkable="false" checked="false" class="android.widget.FrameLayout" clickable="false" content-desc="" enabled="true" focusable="false" focused="false" index="1" long-clickable="false" package="com.instagram.android" password="false" resource-id="com.instagram.android:id/action_bar_textview_custom_title_container" scrollable="false" selected="false" text="">
                                                    <node bounds="[144,90][399,198]" checkable="false" checked="false" class="android.widget.Button" clickable="true" content-desc="Scroll to top" enabled="true" focusable="false" focused="false" index="0" long-clickable="false" package="com.instagram.android" password="false" resource-id="" scrollable="false" selected="false" text="" />
                                                </node>
                                                <node bounds="[792,72][936,216]" checkable="false" checked="false" class="android.widget.ImageView" clickable="true" content-desc="IGTV" enabled="true" focusable="false" focused="false" index="2" long-clickable="true" package="com.instagram.android" password="false" resource-id="" scrollable="false" selected="false" text="" />
                                                <node bounds="[936,72][1080,216]" checkable="false" checked="false" class="android.widget.ImageView" clickable="true" content-desc="Message" enabled="true" focusable="false" focused="false" index="3" long-clickable="true" package="com.instagram.android" password="false" resource-id="com.instagram.android:id/action_bar_inbox_button" scrollable="false" selected="false" text="" />
                                            </node>
                                        </node>
                                        <node bounds="[0,216][1080,237]" checkable="false" checked="false" class="android.view.View" clickable="false" content-desc="" enabled="true" focusable="false" focused="false" index="1" long-clickable="false" package="com.instagram.android" password="false" resource-id="com.instagram.android:id/action_bar_shadow" scrollable="false" selected="false" text="" />
                                    </node>
                                    <node bounds="[0,1611][1080,1632]" checkable="false" checked="false" class="android.view.View" clickable="false" content-desc="" enabled="true" focusable="false" focused="false" index="2" long-clickable="false" package="com.instagram.android" password="false" resource-id="com.instagram.android:id/tab_bar_shadow" scrollable="false" selected="false" text="" />
                                    <node bounds="[0,1632][1080,1776]" checkable="false" checked="false" class="android.widget.LinearLayout" clickable="false" content-desc="" enabled="true" focusable="false" focused="false" index="3" long-clickable="false" package="com.instagram.android" password="false" resource-id="com.instagram.android:id/tab_bar" scrollable="false" selected="false" text="">
                                        <node bounds="[0,1632][216,1776]" checkable="false" checked="false" class="android.widget.FrameLayout" clickable="true" content-desc="Home" enabled="true" focusable="false" focused="false" index="0" long-clickable="false" package="com.instagram.android" password="false" resource-id="" scrollable="false" selected="true" text="">
                                            <node bounds="[72,1668][144,1740]" checkable="false" checked="false" class="android.widget.ImageView" clickable="false" content-desc="" enabled="true" focusable="false" focused="false" index="0" long-clickable="false" package="com.instagram.android" password="false" resource-id="com.instagram.android:id/tab_icon" scrollable="false" selected="true" text="" />
                                        </node>
                                        <node bounds="[216,1632][432,1776]" checkable="false" checked="false" class="android.widget.FrameLayout" clickable="true" content-desc="Search and Explore" enabled="true" focusable="false" focused="false" index="1" long-clickable="true" package="com.instagram.android" password="false" resource-id="" scrollable="false" selected="false" text="">
                                            <node bounds="[288,1668][360,1740]" checkable="false" checked="false" class="android.widget.ImageView" clickable="false" content-desc="" enabled="true" focusable="false" focused="false" index="0" long-clickable="false" package="com.instagram.android" password="false" resource-id="com.instagram.android:id/tab_icon" scrollable="false" selected="false" text="" />
                                        </node>
                                        <node bounds="[432,1632][648,1776]" checkable="false" checked="false" class="android.widget.FrameLayout" clickable="true" content-desc="Camera" enabled="true" focusable="false" focused="false" index="2" long-clickable="true" package="com.instagram.android" password="false" resource-id="" scrollable="false" selected="false" text="">
                                            <node bounds="[504,1668][576,1740]" checkable="false" checked="false" class="android.widget.ImageView" clickable="false" content-desc="" enabled="true" focusable="false" focused="false" index="0" long-clickable="false" package="com.instagram.android" password="false" resource-id="com.instagram.android:id/tab_icon" scrollable="false" selected="false" text="" />
                                        </node>
                                        <node bounds="[648,1632][864,1776]" checkable="false" checked="false" class="android.widget.FrameLayout" clickable="true" content-desc="Activity" enabled="true" focusable="false" focused="false" index="3" long-clickable="false" package="com.instagram.android" password="false" resource-id="" scrollable="false" selected="false" text="">
                                            <node bounds="[720,1668][792,1740]" checkable="false" checked="false" class="android.widget.ImageView" clickable="false" content-desc="" enabled="true" focusable="false" focused="false" index="0" long-clickable="false" package="com.instagram.android" password="false" resource-id="com.instagram.android:id/tab_icon" scrollable="false" selected="false" text="" />
                                        </node>
                                        <node bounds="[864,1632][1080,1776]" checkable="false" checked="false" class="android.widget.FrameLayout" clickable="true" content-desc="Profile" enabled="true" focusable="false" focused="false" index="4" long-clickable="true" package="com.instagram.android" password="false" resource-id="" scrollable="false" selected="false" text="">
                                            <node bounds="[936,1668][1008,1740]" checkable="false" checked="false" class="android.widget.ImageView" clickable="false" content-desc="" enabled="true" focusable="false" focused="false" index="0" long-clickable="false" package="com.instagram.android" password="false" resource-id="com.instagram.android:id/tab_icon" scrollable="false" selected="false" text="" />
                                        </node>
                                    </node>
                                </node>
                                <node bounds="[0,72][1080,1776]" checkable="false" checked="false" class="android.widget.FrameLayout" clickable="false" content-desc="" enabled="true" focusable="false" focused="false" index="2" long-clickable="false" package="com.instagram.android" password="false" resource-id="com.instagram.android:id/bottom_sheet_container" scrollable="false" selected="false" text="" />
                            </node>
                        </node>
                    </node>
                </node>
            </node>
        </node>
        <node bounds="[0,0][1080,72]" checkable="false" checked="false" class="android.view.View" clickable="false" content-desc="" enabled="true" focusable="false" focused="false" index="1" long-clickable="false" package="com.instagram.android" password="false" resource-id="android:id/statusBarBackground" scrollable="false" selected="false" text="" />
        <node bounds="[0,0][0,0]" checkable="false" checked="false" class="android.view.View" clickable="false" content-desc="" enabled="true" focusable="false" focused="false" index="2" long-clickable="false" package="com.instagram.android" password="false" resource-id="android:id/navigationBarBackground" scrollable="false" selected="false" text="" />
    </node>
</hierarchy>